[{"line":2,"elements":[{"start_timestamp":"2023-06-07T13:34:34.609Z","before":[{"result":{"duration":4270856800,"status":"passed"},"match":{"location":"com.unifiedframework.api.hooks.APIHooks.setup()"}}],"line":5,"name":"Verify Delete Users api","description":"","id":"delete-users-api--delete-existing-users;verify-delete-users-api","type":"scenario","keyword":"Scenario","steps":[{"result":{"duration":959515500,"status":"passed"},"line":6,"name":"a user submits valid delete users request","match":{"location":"com.unifiedframework.api.stepdefinitions.APISteps.a_user_submits_valid_delete_users_request()"},"keyword":"Given "},{"result":{"error_message":"java.lang.AssertionError: expected [200] but found [405]\r\n\tat org.testng.Assert.fail(Assert.java:99)\r\n\tat org.testng.Assert.failNotEquals(Assert.java:1037)\r\n\tat org.testng.Assert.assertEqualsImpl(Assert.java:140)\r\n\tat org.testng.Assert.assertEquals(Assert.java:122)\r\n\tat org.testng.Assert.assertEquals(Assert.java:907)\r\n\tat org.testng.Assert.assertEquals(Assert.java:917)\r\n\tat com.unifiedframework.api.stepdefinitions.APISteps.a_success_response_is_received(APISteps.java:192)\r\n\tat ✽.a success response is received(file:///D:/Selenium/Eclipse20-23/UnifiedFramework/src/test/java/com/unifiedframework/api/features/DeleteUser.feature:7)\r\n","duration":6777900,"status":"failed"},"line":7,"name":"a success response is received","match":{"location":"com.unifiedframework.api.stepdefinitions.APISteps.a_success_response_is_received()"},"keyword":"When "},{"result":{"status":"skipped"},"line":8,"name":"verify response time, size","match":{"location":"com.unifiedframework.api.stepdefinitions.APISteps.verify_response_size_time()"},"keyword":"Then "}],"tags":[{"name":"@API"},{"name":"@DeleteUser"},{"name":"@Success"}]}],"name":"Delete Users api, delete existing users","description":"","id":"delete-users-api--delete-existing-users","keyword":"Feature","uri":"file:src/test/java/com/unifiedframework/api/features/DeleteUser.feature","tags":[{"name":"@API","type":"Tag","location":{"line":1,"column":1}},{"name":"@DeleteUser","type":"Tag","location":{"line":1,"column":6}}]},{"line":2,"elements":[{"start_timestamp":"2023-06-07T13:34:40.077Z","before":[{"result":{"duration":567691000,"status":"passed"},"match":{"location":"com.unifiedframework.api.hooks.APIHooks.setup()"}}],"line":5,"name":"Verify Get Users api","description":"","id":"get-users-api--list-all-activities;verify-get-users-api","type":"scenario","keyword":"Scenario","steps":[{"result":{"duration":362151400,"status":"passed"},"line":6,"name":"a user submits valid get users request","match":{"location":"com.unifiedframework.api.stepdefinitions.APISteps.a_user_submits_valid_get_users_request()"},"keyword":"Given "},{"result":{"duration":999500,"status":"passed"},"line":7,"name":"a success response is received","match":{"location":"com.unifiedframework.api.stepdefinitions.APISteps.a_success_response_is_received()"},"keyword":"When "},{"result":{"status":"passed"},"line":8,"name":"verify response time, size","match":{"location":"com.unifiedframework.api.stepdefinitions.APISteps.verify_response_size_time()"},"keyword":"Then "},{"result":{"duration":721087900,"status":"passed"},"line":9,"name":"verify getUsers response schema","match":{"arguments":[{"val":"getUsers","offset":7}],"location":"com.unifiedframework.api.stepdefinitions.APISteps.verify_response_schema(java.lang.String)"},"keyword":"And "}],"tags":[{"name":"@API"},{"name":"@GetUsers"},{"name":"@Success"}]}],"name":"Get Users api, list all activities","description":"","id":"get-users-api--list-all-activities","keyword":"Feature","uri":"file:src/test/java/com/unifiedframework/api/features/GetUsers.feature","tags":[{"name":"@API","type":"Tag","location":{"line":1,"column":1}},{"name":"@GetUsers","type":"Tag","location":{"line":1,"column":6}}]},{"line":2,"elements":[{"start_timestamp":"2023-06-07T13:34:41.750Z","before":[{"result":{"duration":358391000,"status":"passed"},"match":{"location":"com.unifiedframework.api.hooks.APIHooks.setup()"}}],"line":5,"name":"Verify create Users api","description":"","id":"post-users-api--create-users;verify-create-users-api","type":"scenario","keyword":"Scenario","steps":[{"result":{"duration":326160100,"status":"passed"},"line":6,"name":"a user submits valid create users request","match":{"location":"com.unifiedframework.api.stepdefinitions.APISteps.a_user_submits_valid_create_users_request()"},"keyword":"Given "},{"result":{"duration":1021100,"status":"passed"},"line":7,"name":"a success response is received","match":{"location":"com.unifiedframework.api.stepdefinitions.APISteps.a_success_response_is_received()"},"keyword":"When "},{"result":{"duration":998300,"status":"passed"},"line":8,"name":"verify response time, size","match":{"location":"com.unifiedframework.api.stepdefinitions.APISteps.verify_response_size_time()"},"keyword":"Then "},{"result":{"duration":997300,"status":"passed"},"line":9,"name":"verify createUsers response schema","match":{"arguments":[{"val":"createUsers","offset":7}],"location":"com.unifiedframework.api.stepdefinitions.APISteps.verify_response_schema(java.lang.String)"},"keyword":"And "}],"tags":[{"name":"@API"},{"name":"@Success"}]}],"name":"Post Users api, create users","description":"","id":"post-users-api--create-users","keyword":"Feature","uri":"file:src/test/java/com/unifiedframework/api/features/PostUser.feature","tags":[{"name":"@API","type":"Tag","location":{"line":1,"column":1}}]},{"line":2,"elements":[{"start_timestamp":"2023-06-07T13:34:42.457Z","before":[{"result":{"duration":318961100,"status":"passed"},"match":{"location":"com.unifiedframework.api.hooks.APIHooks.setup()"}}],"line":5,"name":"Verify Update Users api","description":"","id":"put-users-api--update-existing-users;verify-update-users-api","type":"scenario","keyword":"Scenario","steps":[{"result":{"duration":668558800,"status":"passed"},"line":6,"name":"a user submits valid update users request","match":{"location":"com.unifiedframework.api.stepdefinitions.APISteps.a_user_submits_valid_update_users_request()"},"keyword":"Given "},{"result":{"error_message":"java.lang.AssertionError: expected [200] but found [405]\r\n\tat org.testng.Assert.fail(Assert.java:99)\r\n\tat org.testng.Assert.failNotEquals(Assert.java:1037)\r\n\tat org.testng.Assert.assertEqualsImpl(Assert.java:140)\r\n\tat org.testng.Assert.assertEquals(Assert.java:122)\r\n\tat org.testng.Assert.assertEquals(Assert.java:907)\r\n\tat org.testng.Assert.assertEquals(Assert.java:917)\r\n\tat com.unifiedframework.api.stepdefinitions.APISteps.a_success_response_is_received(APISteps.java:192)\r\n\tat ✽.a success response is received(file:///D:/Selenium/Eclipse20-23/UnifiedFramework/src/test/java/com/unifiedframework/api/features/UpdateUser.feature:7)\r\n","duration":998500,"status":"failed"},"line":7,"name":"a success response is received","match":{"location":"com.unifiedframework.api.stepdefinitions.APISteps.a_success_response_is_received()"},"keyword":"When "},{"result":{"duration":1027000,"status":"skipped"},"line":8,"name":"verify response time, size","match":{"location":"com.unifiedframework.api.stepdefinitions.APISteps.verify_response_size_time()"},"keyword":"Then "},{"result":{"status":"skipped"},"line":9,"name":"verify updateUsers response schema","match":{"arguments":[{"val":"updateUsers","offset":7}],"location":"com.unifiedframework.api.stepdefinitions.APISteps.verify_response_schema(java.lang.String)"},"keyword":"And "},{"result":{"duration":999600,"status":"skipped"},"line":10,"name":"verify the result using get api","match":{"location":"com.unifiedframework.api.stepdefinitions.APISteps.verify_the_result_using_get_api()"},"keyword":"And "}],"tags":[{"name":"@API"},{"name":"@UpdateUser"},{"name":"@Success"}]}],"name":"Put Users api, update existing users","description":"","id":"put-users-api--update-existing-users","keyword":"Feature","uri":"file:src/test/java/com/unifiedframework/api/features/UpdateUser.feature","tags":[{"name":"@API","type":"Tag","location":{"line":1,"column":1}},{"name":"@UpdateUser","type":"Tag","location":{"line":1,"column":6}}]}]